sphinx_argparse_cli/__init__.py
sphinx_argparse_cli/_logic.py
sphinx_argparse_cli/py.typed
sphinx_argparse_cli/version.py
sphinx_argparse_cli-1.20.1.dist-info/METADATA
sphinx_argparse_cli-1.20.1.dist-info/WHEEL
sphinx_argparse_cli-1.20.1.dist-info/licenses/LICENSE.txt
sphinx_argparse_cli-1.20.1.dist-info/RECORD
